scanprep/__init__.py
scanprep/scanprep.py
scanprep-1.0.2.dist-info/LICENSE
scanprep-1.0.2.dist-info/METADATA
scanprep-1.0.2.dist-info/WHEEL
scanprep-1.0.2.dist-info/entry_points.txt
scanprep-1.0.2.dist-info/top_level.txt
scanprep-1.0.2.dist-info/RECORD
