Metadata-Version: 2.1
Name: scanprep
Version: 1.0.2
Summary: Small utility to prepare scanned documents. Supports separating PDF files by separator pages and removing blank pages.
Home-page: https://github.com/baltpeter/scanprep
Author: Benjamin Altpeter
Author-email: hi@bn.al
License: UNKNOWN
Platform: UNKNOWN
Classifier: Programming Language :: Python :: 3
Classifier: License :: OSI Approved :: MIT License
Classifier: Operating System :: OS Independent
Requires-Python: >=3.6
Requires-Dist: numpy (==1.19.5)
Requires-Dist: pillow (==8.1.0)
Requires-Dist: pymupdf (==1.18.6)
Requires-Dist: pyzbar (==0.1.8)
